odoo/addons/ddmrp_sale_dropshipping/README.rst
odoo/addons/ddmrp_sale_dropshipping/__init__.py
odoo/addons/ddmrp_sale_dropshipping/__manifest__.py
odoo/addons/ddmrp_sale_dropshipping/i18n/ddmrp_sale_dropshipping.pot
odoo/addons/ddmrp_sale_dropshipping/i18n/it.po
odoo/addons/ddmrp_sale_dropshipping/models/__init__.py
odoo/addons/ddmrp_sale_dropshipping/models/stock_buffer.py
odoo/addons/ddmrp_sale_dropshipping/readme/CONTRIBUTORS.rst
odoo/addons/ddmrp_sale_dropshipping/readme/DESCRIPTION.rst
odoo/addons/ddmrp_sale_dropshipping/static/description/icon.png
odoo/addons/ddmrp_sale_dropshipping/static/description/index.html
odoo/addons/ddmrp_sale_dropshipping/tests/__init__.py
odoo/addons/ddmrp_sale_dropshipping/tests/test_ddmrp_sale_dropshipping.py
odoo_addon_ddmrp_sale_dropshipping-16.0.1.0.0.4.dist-info/METADATA
odoo_addon_ddmrp_sale_dropshipping-16.0.1.0.0.4.dist-info/WHEEL
odoo_addon_ddmrp_sale_dropshipping-16.0.1.0.0.4.dist-info/top_level.txt
odoo_addon_ddmrp_sale_dropshipping-16.0.1.0.0.4.dist-info/RECORD
