Metadata-Version: 2.1
Name: odoo-addon-ddmrp_sale_dropshipping
Version: 16.0.1.0.0.4
Summary: Ignore qualified demand of sale quotes that are dropshipped.
Home-page: https://github.com/OCA/ddmrp
Author: ForgeFlow, Odoo Community Association (OCA)
Author-email: support@odoo-community.org
License: AGPL-3
Classifier: Programming Language :: Python
Classifier: Framework :: Odoo
Classifier: Framework :: Odoo :: 16.0
Classifier: License :: OSI Approved :: GNU Affero General Public License v3
Classifier: Development Status :: 4 - Beta
Requires-Python: >=3.10
Requires-Dist: odoo-addon-ddmrp-sale <16.1dev,>=16.0dev
Requires-Dist: odoo <16.1dev,>=16.0a
